<?xml version="1.0" encoding="UTF-8"?><listing uri="/50/RDO+50+-+SOUTH+MAKATI/MAKATI+CITY/BEL+AIR+(SALCEDO+VILLAGE)/LPL+CENTER/SAN+AGUSTIN+NEAR+COR+SEDE%c3%91O/RC/CONDO/Sheet+7+(DO+1-2012).xml" index="143"><rdo nr="50">RDO 50 - SOUTH MAKATI</rdo><city>MAKATI CITY</city><barangay>BEL AIR (SALCEDO VILLAGE)</barangay><condo>LPL CENTER</condo><vicinity>SAN AGUSTIN NEAR COR SEDEÑO</vicinity><class>RC</class><rev>60000</rev><start-date iso-date="2012-03-09">09-03-2012</start-date><end-date iso-date="2050-01-01">Present</end-date><do-no>1-2012</do-no><revision>6th</revision></listing>